<annotation>
	<folder>Acne Studios</folder>
	<filename>00001-Acne-Studios-Mens-Fall-21.jpg</filename>
	<path>D:\Ambaram\Vogue\Acne Studios\00001-Acne-Studios-Mens-Fall-21.jpg</path>
	<source>
		<database>Unknown</database>
	</source>
	<size>
		<width>480</width>
		<height>720</height>
		<depth>3</depth>
	</size>
	<segmented>0</segmented>
	<object>
		<name>coat,knit</name>
		<pose>Unspecified</pose>
		<truncated>0</truncated>
		<difficult>0</difficult>
		<bndbox>
			<xmin>147</xmin>
			<ymin>159</ymin>
			<xmax>343</xmax>
			<ymax>452</ymax>
		</bndbox>
	</object>
	<object>
		<name>gloves</name>
		<pose>Unspecified</pose>
		<truncated>0</truncated>
		<difficult>0</difficult>
		<bndbox>
			<xmin>151</xmin>
			<ymin>392</ymin>
			<xmax>183</xmax>
			<ymax>425</ymax>
		</bndbox>
	</object>
	<object>
		<name>gloves</name>
		<pose>Unspecified</pose>
		<truncated>0</truncated>
		<difficult>0</difficult>
		<bndbox>
			<xmin>284</xmin>
			<ymin>388</ymin>
			<xmax>322</xmax>
			<ymax>426</ymax>
		</bndbox>
	</object>
	<object>
		<name>shoes</name>
		<pose>Unspecified</pose>
		<truncated>0</truncated>
		<difficult>0</difficult>
		<bndbox>
			<xmin>133</xmin>
			<ymin>555</ymin>
			<xmax>226</xmax>
			<ymax>650</ymax>
		</bndbox>
	</object>
	<object>
		<name>shoes</name>
		<pose>Unspecified</pose>
		<truncated>0</truncated>
		<difficult>0</difficult>
		<bndbox>
			<xmin>229</xmin>
			<ymin>559</ymin>
			<xmax>282</xmax>
			<ymax>660</ymax>
		</bndbox>
	</object>
</annotation>
